{
    "data": [
        {
            "id": 1,
            "name": "Fabuloso Antibacterial 2L",
            "alt": "Fabuloso",
            "precio": 12200,
            "medida": "U",
            "popularidad": "1",
            "image": "https://i.ibb.co/thfB73M/Name-Fabuloso.jpg"
        },
        {
            "id": 2,
            "name": "Huevos Paquete 18U",
            "alt": "Huevos",
            "precio": 9600,
            "medida": "U",
            "popularidad": "3",
            "image": "https://i.ibb.co/JQMCQTJ/Name-Huevos.jpg"
        },
        {
            "id": 3,
            "name": "Colgate Pasta Dental Triple Familiar EconoPack",
            "alt": "Colgate-Pasta-Dental",
            "precio": 14900,
            "medida": "U",
            "popularidad": "5",
            "image": "https://i.ibb.co/KhBMGS7/Name-Colgate.jpg"
        },
        {
            "id": 4,
            "name": "Mc. Cornick Mayonesa 500g",
            "alt": "Mayonesa-Mc-Cornick",
            "precio": 31000,
            "medida": "U",
            "popularidad": "5",
            "image": "https://i.ibb.co/MSdS2C4/Name-Mc-Cormick-Mayonesa.jpg"
        },
        {
            "id": 5,
            "name": "Pan Bimbo Blanco Grande",
            "alt": "Pan-Bimbo",
            "precio": 4890,
            "medida": "U",
            "popularidad": "5",
            "image": "https://i.ibb.co/RgX5J1X/Name-Pan-Bimbo.jpg"
        },
        {
            "id": 6,
            "name": "San Rafael Pechuga de pavo Paquete 500g",
            "alt": "Jamon-de-Pavo",
            "precio": 9900,
            "medida": "U",
            "popularidad": "5",
            "image": "https://i.ibb.co/ypqD9c0/Name-Pechuga-de-pavo.jpg"
        },
        {
            "id": 7,
            "name": "Manzana Golden",
            "alt": "Manzana-Golden",
            "precio": 4300,
            "medida": 500,
            "popularidad": "2",
            "image": "https://i.ibb.co/72sfTFb/Name-Manzana-Golden.jpg"
        },
        {
            "id": 8,
            "name": "Tomate Chonto",
            "alt": "Tomate",
            "precio": 1500,
            "medida": 500,
            "popularidad": "2",
            "image": "https://i.ibb.co/0tWxXjQ/Name-Jitomate-Bola.jpg"
        },
        {
            "id": 9,
            "name": "Naranja",
            "alt": "Naranja",
            "precio": 900,
            "medida": 500,
            "popularidad": "5",
            "image": "https://i.ibb.co/YtrkDzv/Name-Naranja.jpg"
        },
        {
            "id": 10,
            "name": "Gaseosa Coca-Cola 600 ml",
            "alt": "Coca-Cola",
            "precio": 2390,
            "medida": "U",
            "popularidad": "4",
            "image": "https://i.ibb.co/JrFxWKC/Name-Cocacola.jpg"
        },
        {
            "id": 11,
            "name": "Gaseosa Coca-Cola Sin Azúcar 600 ml",
            "alt": "Coca-Sin-Azucar",
            "precio": 2290,
            "medida": "U",
            "popularidad": "4",
            "image": "https://i.ibb.co/gdZtV0j/Name-Cocacola-sin-azucar.jpg"
        },
        {
            "id": 12,
            "name": "Tomate Chonto Verde",
            "alt": "Tomate-Verde",
            "precio": 1500,
            "medida": "U",
            "popularidad": "1",
            "image": "https://i.ibb.co/0KXKn4Z/Name-Tomate-verde.jpg"
        },
        {
            "id": 13,
            "name": "Nopal Importado",
            "alt": "Nopal",
            "precio": 3500,
            "medida": 500,
            "popularidad": "3",
            "image": "https://i.ibb.co/QMG6nxS/Name-Nopal.jpg"
        },
        {
            "id": 13,
            "name": "Aguacate Hass",
            "alt": "Aguacate-Hass",
            "precio": 4690,
            "medida": 500,
            "popularidad": "5",
            "image": "https://i.ibb.co/D1580yy/Name-Aguacate.jpg"
        },
        {
            "id": 13,
            "name": "Tomate Importado",
            "alt": "Tomate-Importado",
            "precio": 2090,
            "medida": 500,
            "popularidad": "4",
            "image": "https://i.ibb.co/Q8gHNHP/Name-Tomate.jpg"
        },
        {
            "id": 13,
            "name": "Limon Tahiti",
            "alt": "Limon",
            "precio": 1090,
            "medida": 500,
            "popularidad": "4",
            "image": "https://i.ibb.co/kqj4Qz4/Name-Limon.jpg"
        }
    
    ]
}